data_axolotl/__about__.py
data_axolotl/__init__.py
data_axolotl/__main__.py
data_axolotl/alert_report.py
data_axolotl/api.py
data_axolotl/cli.py
data_axolotl/config.py
data_axolotl/database_types.py
data_axolotl/derived_metrics.py
data_axolotl/display_utils.py
data_axolotl/generate_config_interactive.py
data_axolotl/history_report.py
data_axolotl/line_chart.py
data_axolotl/live_run_console.py
data_axolotl/metric_query.py
data_axolotl/metric_set.py
data_axolotl/snapshot_snowflake.py
data_axolotl/snowflake_utils.py
data_axolotl/test_snowflake_connection.py
data_axolotl/timeouts.py
data_axolotl/trackers.py
data_axolotl/utils.py
data_axolotl/connectors/base_connection.py
data_axolotl/connectors/identifiers.py
data_axolotl/connectors/parallel_query_executor.py
data_axolotl/connectors/snowflake_connection.py
data_axolotl/connectors/sqlite_connection.py
data_axolotl/connectors/state_dao.py
data_axolotl-0.1.1.dist-info/METADATA
data_axolotl-0.1.1.dist-info/WHEEL
data_axolotl-0.1.1.dist-info/entry_points.txt
data_axolotl-0.1.1.dist-info/licenses/LICENSE.txt
data_axolotl-0.1.1.dist-info/RECORD
