Metadata-Version: 2.4
Name: data-axolotl
Version: 0.1.1
Project-URL: Documentation, https://github.com/thorntale/data-axolotl#readme
Project-URL: Issues, https://github.com/thorntale/data-axolotl/issues
Project-URL: Source, https://github.com/thorntale/data-axolotl
Author-email: Thorntale <support@thorntale.com>
License-Expression: MIT
License-File: LICENSE.txt
Classifier: Development Status :: 4 - Beta
Classifier: Programming Language :: Python
Classifier: Programming Language :: Python :: 3.8
Classifier: Programming Language :: Python :: 3.9
Classifier: Programming Language :: Python :: 3.10
Classifier: Programming Language :: Python :: 3.11
Classifier: Programming Language :: Python :: 3.12
Classifier: Programming Language :: Python :: Implementation :: CPython
Classifier: Programming Language :: Python :: Implementation :: PyPy
Requires-Python: >=3.12
Requires-Dist: cryptography>=41.0.0
Requires-Dist: humanize>=4.13.0
Requires-Dist: pandas
Requires-Dist: pydantic>=2.0.0
Requires-Dist: pyyaml
Requires-Dist: readchar
Requires-Dist: simplejson>=3.20.0
Requires-Dist: snowflake-connector-python[pandas]>=3.18.0
Requires-Dist: tabulate>=0.9.0
Requires-Dist: typer>=0.9.0
